[
  {
    "answer": "Kelurahan Cipinang Melayu merupakan salah satu kelurahan yang berada di wilayah Kota Administrasi Jakarta Timur.",
    "category_id": 1,
    "question": "Apa itu Kelurahan Cipinang Melayu?"
  },
  {
    "answer": "Lurah Kelurahan Cipinang Melayu saat ini adalah Bapak Arroyantoro.",
    "category_id": 2,
    "question": "Siapa Lurah Kelurahan Cipinang Melayu"
  },
  {
    "answer": "Kantor Kelurahan Cipinang Melayu berlokasi di Jl. Borobudur, RT 1/RW 10, Cipinang Melayu, Kecamatan Makasar, Kota Jakarta Timur, Daerah Khusus Ibukota Jakarta 13620.",
    "category_id": 2,
    "question": "Di mana letak Kantor Kelurahan Cipinang Melayu?"
  },
  {
    "answer": "Kelurahan Cipinang Melayu menyediakan layanan admiinistrasi kependudukan seperti pengurusan kk",
    "category_id": 2,
    "question": "Apa saja layanan yang tersedia di Kelurahan Cipinang Melayu"
  },
  {
    "answer": "Kelurahan Cipinang Melayu melayani berbagai surat administrasi seperti surat pengantar KTP, KK, surat keterangan domisili, surat keterangan usaha, dan surat keterangan tidak mampu.",
    "category_id": 1,
    "question": "Apa saja jenis surat administrasi yang dapat diurus di Kelurahan Cipinang Melayu?"
  },
  {
    "answer": "Syarat umum meliputi fotokopi KTP, Kartu Keluarga, dan dokumen pendukung sesuai jenis surat yang diajukan.",
    "category_id": 1,
    "question": "Apa syarat umum pengurusan surat administrasi?"
  },
  {
    "answer": "Seluruh pengurusan surat administrasi di kelurahan tidak dipungut biaya.",
    "category_id": 1,
    "question": "Apakah pengurusan surat administrasi dikenakan biaya?"
  },
  {
    "answer": "Proses pembuatan surat umumnya memakan waktu 1 hari kerja, tergantung kelengkapan berkas.",
    "category_id": 1,
    "question": "Berapa lama proses pembuatan surat administrasi?"
  },
  {
    "answer": "Pengurusan surat dapat diwakilkan dengan membawa surat kuasa dan dokumen pendukung.",
    "category_id": 1,
    "question": "Apakah pengurusan surat dapat diwakilkan?"
  },
  {
    "answer": "Untuk saat ini, pengurusan surat administrasi dilakukan dengan datang langsung ke kantor kelurahan.",
    "category_id": 1,
    "question": "Apakah warga harus datang langsung ke kantor kelurahan?"
  },
  {
    "answer": "Jika berkas lengkap, surat dapat diambil pada hari yang sama sesuai ketentuan petugas.",
    "category_id": 1,
    "question": "Apakah surat yang sudah jadi dapat diambil di hari yang sama?"
  },
  {
    "answer": "Ya, formulir pengajuan surat tersedia di kantor kelurahan.",
    "category_id": 1,
    "question": "Apakah tersedia formulir pengajuan surat di kelurahan?"
  },
  {
    "answer": "Beberapa jenis surat memerlukan surat pengantar dari RT/RW setempat.",
    "category_id": 1,
    "question": "Apakah warga perlu membawa surat pengantar RT/RW?"
  },
  {
    "answer": "Jika berkas tidak lengkap, pemohon akan diminta melengkapi persyaratan terlebih dahulu.",
    "category_id": 1,
    "question": "Bagaimana jika berkas pengajuan tidak lengkap?"
  },
  {
    "answer": "Pelayanan dibuka pada hari Senin sampai Jumat pukul 08.00–16.00 WIB.",
    "category_id": 2,
    "question": "Jam operasional pelayanan Kelurahan Cipinang Melayu pukul berapa?"
  },
  {
    "answer": "Pelayanan hanya diberikan kepada warga yang berdomisili di wilayah Kelurahan Cipinang Melayu.",
    "category_id": 2,
    "question": "Apakah kelurahan melayani warga di luar wilayah Cipinang Melayu?"
  },
  {
    "answer": "Sebagian besar layanan dilakukan secara langsung di kantor kelurahan.",
    "category_id": 2,
    "question": "Apakah semua layanan dilakukan secara langsung?"
  },
  {
    "answer": "Informasi kontak resmi dapat diperoleh langsung di kantor kelurahan.",
    "category_id": 2,
    "question": "Apakah tersedia nomor kontak resmi kelurahan?"
  },
  {
    "answer": "Keluhan dapat disampaikan langsung kepada petugas kelurahan saat jam kerja.",
    "category_id": 2,
    "question": "Bagaimana prosedur penyampaian keluhan pelayanan?"
  },
  {
    "answer": "Warga lanjut usia dan berkebutuhan khusus akan mendapatkan prioritas pelayanan.",
    "category_id": 2,
    "question": "Apakah warga lanjut usia mendapat prioritas pelayanan?"
  },
  {
    "answer": "Seluruh pelayanan dilaksanakan sesuai dengan SOP yang berlaku.",
    "category_id": 2,
    "question": "Apakah pelayanan dilakukan sesuai standar operasional prosedur (SOP)?"
  },
  {
    "answer": "Pelayanan tutup pada hari libur nasional dan cuti bersama.",
    "category_id": 2,
    "question": "Apakah pelayanan tetap buka saat hari libur nasional?"
  },
  {
    "answer": "a, kelurahan menyediakan layanan konsultasi terkait administrasi dan pelayanan umum.",
    "category_id": 2,
    "question": "Apakah tersedia layanan konsultasi bagi warga?"
  },
  {
    "answer": "Kelurahan membantu administrasi perpajakan berupa surat keterangan dan surat pengantar.",
    "category_id": 3,
    "question": "Layanan perpajakan apa saja yang dapat dibantu oleh kelurahan?"
  },
  {
    "answer": "Kelurahan tidak melayani pembayaran pajak secara langsung.",
    "category_id": 3,
    "question": "Apakah kelurahan melayani pembayaran pajak secara langsung?"
  },
  {
    "answer": "Dokumen yang dibutuhkan antara lain KTP, KK, dan dokumen pajak terkait.",
    "category_id": 3,
    "question": "Dokumen apa saja yang dibutuhkan untuk pengurusan administrasi pajak?"
  },
  {
    "answer": "Ya, warga dapat berkonsultasi mengenai prosedur perpajakan dengan petugas kelurahan.",
    "category_id": 3,
    "question": "Apakah warga dapat berkonsultasi mengenai pajak di kelurahan?"
  },
  {
    "answer": "Kelurahan membantu pengurusan administrasi dan informasi terkait PBB.",
    "category_id": 3,
    "question": "Apakah kelurahan melayani pengurusan PBB?"
  },
  {
    "answer": "Kelurahan tidak mencetak bukti pembayaran pajak.",
    "category_id": 3,
    "question": "Apakah kelurahan dapat mencetak bukti pembayaran pajak?"
  },
  {
    "answer": "Warga diarahkan ke instansi atau layanan resmi yang ditunjuk pemerintah daerah.",
    "category_id": 3,
    "question": "Ke mana warga diarahkan untuk melakukan pembayaran pajak?"
  },
  {
    "answer": "Pengurusan administrasi pajak dilakukan pada jam kerja kelurahan.",
    "category_id": 3,
    "question": "Apakah ada batas waktu pengurusan administrasi pajak di kelurahan?"
  },
  {
    "answer": "Pengurusan administrasi perpajakan tidak dikenakan biaya.",
    "category_id": 3,
    "question": "Apakah pengurusan administrasi pajak dikenakan biaya?"
  },
  {
    "answer": "Warga dapat menghubungi petugas kelurahan pada jam pelayanan untuk mendapatkan informasi lebih lanjut.",
    "category_id": 3,
    "question": "Siapa yang dapat dihubungi jika terdapat kendala terkait pajak?"
  },
  {
    "answer": "Pengajuan surat administrasi dapat dilakukan selama jam operasional kelurahan pada hari kerja.",
    "category_id": 1,
    "question": "Apakah pengajuan surat administrasi memiliki batas waktu tertentu?"
  },
  {
    "answer": "Beberapa jenis surat administrasi memiliki masa berlaku tertentu sesuai dengan ketentuan yang berlaku.",
    "category_id": 1,
    "question": "Apakah surat administrasi memiliki masa berlaku?"
  },
  {
    "answer": "Ya, data pemohon dijaga kerahasiaannya dan hanya digunakan untuk keperluan administrasi.",
    "category_id": 1,
    "question": "Apakah data pemohon dijamin kerahasiaannya?"
  },
  {
    "answer": "Kelurahan menyediakan bantuan dan pendampingan bagi warga yang membutuhkan informasi terkait prosedur pengurusan surat administrasi.",
    "category_id": 1,
    "question": "Apakah kelurahan menyediakan bantuan bagi warga yang belum memahami prosedur pengurusan surat?"
  },
  {
    "answer": "Ya, warga diwajibkan membawa dokumen asli sebagai bahan verifikasi saat mengurus pelayanan di kelurahan.",
    "category_id": 2,
    "question": "Apakah warga perlu membawa dokumen asli saat mengurus pelayanan?"
  },
  {
    "answer": "Ya, pelayanan kelurahan menerapkan sistem antrean untuk menjaga ketertiban dan kenyamanan warga.",
    "category_id": 2,
    "question": "Apakah pelayanan kelurahan menerapkan sistem antrean?"
  },
  {
    "answer": "Kelurahan menyediakan ruang tunggu bagi warga yang sedang menunggu pelayanan.",
    "category_id": 2,
    "question": "Apakah tersedia fasilitas ruang tunggu bagi warga?"
  },
  {
    "answer": "Kelurahan membantu administrasi perpajakan berupa pemberian informasi, surat keterangan, dan surat pengantar terkait pajak daerah.",
    "category_id": 3,
    "question": "Layanan perpajakan apa saja yang dapat dibantu oleh Kelurahan Cipinang Melayu?"
  },
  {
    "answer": "Tidak, kelurahan tidak melayani pembayaran pajak secara langsung.",
    "category_id": 3,
    "question": "Apakah kelurahan melayani pembayaran pajak secara langsung?"
  },
  {
    "answer": "Kelurahan dapat membantu memberikan arahan dan surat pengantar apabila terdapat permasalahan data wajib pajak.",
    "category_id": 3,
    "question": "Apakah kelurahan membantu pengurusan data wajib pajak yang bermasalah?"
  },
  {
    "answer": "Kelurahan membantu proses administrasi berupa surat pengantar sesuai dengan ketentuan yang berlaku.",
    "category_id": 3,
    "question": "Apakah kelurahan melayani permohonan surat keterangan bebas tunggakan pajak?"
  },
  {
    "answer": "Ya, informasi perpajakan yang disampaikan mengikuti kebijakan dan ketentuan terbaru dari pemerintah daerah.",
    "category_id": 3,
    "question": "Apakah informasi perpajakan yang diberikan kelurahan selalu diperbarui?"
  },
  {
    "answer": "Kelurahan melayani administrasi kependudukan seperti surat pengantar KTP, KK, pindah datang, dan perubahan data.",
    "category_id": 4,
    "question": "Layanan kependudukan apa saja yang dapat diurus di kelurahan?"
  },
  {
    "answer": "Kelurahan tidak mencetak KTP, tetapi membantu proses administrasi dan surat pengantar.",
    "category_id": 4,
    "question": "Apakah kelurahan melayani pembuatan KTP secara langsung?"
  },
  {
    "answer": "Syarat meliputi KTP, KK, dan dokumen pendukung sesuai jenis perubahan data.",
    "category_id": 4,
    "question": "Apa saja syarat pengurusan perubahan data kependudukan?"
  },
  {
    "answer": "Kelurahan membantu proses pengurusan melalui surat pengantar dan verifikasi data.",
    "category_id": 4,
    "question": "Apakah pengurusan KK bisa dilakukan di kelurahan?"
  },
  {
    "answer": "Ya, pendaftaran diperlukan sebagai bagian dari administrasi kependudukan.",
    "category_id": 4,
    "question": "Apakah bayi baru lahir perlu didaftarkan ke kelurahan?"
  },
  {
    "answer": "Ya, kelurahan melayani pembuatan surat keterangan pindah bagi warga.",
    "category_id": 4,
    "question": "Apakah kelurahan melayani surat keterangan pindah?"
  },
  {
    "answer": "Kelurahan membantu administrasi pembaruan data sesuai ketentuan.",
    "category_id": 4,
    "question": "Apakah kelurahan melayani pembaruan status perkawinan?"
  },
  {
    "answer": "Ya, warga dapat berkonsultasi dengan petugas kelurahan.",
    "category_id": 4,
    "question": "Apakah warga dapat berkonsultasi terkait kependudukan?"
  },
  {
    "answer": "Bantuan sosial meliputi program pemerintah pusat dan daerah.",
    "category_id": 5,
    "question": "Apa saja jenis bantuan sosial yang tersedia?"
  },
  {
    "answer": "Kelurahan membantu pendataan dan verifikasi, bukan penentu akhir.",
    "category_id": 5,
    "question": "Apakah kelurahan menentukan penerima bantuan sosial?"
  },
  {
    "answer": "Pendaftaran dilakukan melalui pendataan kelurahan dan RT/RW.",
    "category_id": 5,
    "question": "Bagaimana cara mendaftar sebagai penerima bantuan sosial?"
  },
  {
    "answer": "Syarat mengikuti ketentuan program bantuan yang berlaku.",
    "category_id": 5,
    "question": "Apa syarat umum penerima bantuan sosial?"
  },
  {
    "answer": "Waktu penyaluran tergantung kebijakan program.",
    "category_id": 5,
    "question": "Apakah bantuan sosial diberikan setiap bulan?"
  },
  {
    "answer": "Warga dapat menyampaikan pengaduan ke kelurahan.",
    "category_id": 5,
    "question": "Bagaimana jika warga merasa layak tetapi belum menerima bantuan?"
  },
  {
    "answer": "Ya, kelurahan membantu pengecekan data kepesertaan.",
    "category_id": 5,
    "question": "Apakah kelurahan membantu pengecekan data bansos?"
  },
  {
    "answer": "Bantuan dapat berupa uang tunai atau barang.",
    "category_id": 5,
    "question": "Apakah bantuan sosial berbentuk uang atau barang?"
  },
  {
    "answer": "Ya, sesuai ketentuan program bantuan.",
    "category_id": 5,
    "question": "Apakah lansia dan disabilitas mendapat prioritas bantuan sosial?"
  },
  {
    "answer": "Ya, data dapat diperbarui melalui pendataan ulang.",
    "category_id": 5,
    "question": "Apakah data penerima bantuan dapat diperbarui?"
  },
  {
    "answer": "Warga dapat melapor ke kelurahan untuk ditindaklanjuti.",
    "category_id": 5,
    "question": "Bagaimana jika data bantuan tidak sesuai?"
  },
  {
    "answer": "Penyaluran mengikuti mekanisme instansi terkait.",
    "category_id": 5,
    "question": "Apakah kelurahan menyalurkan bantuan langsung?"
  },
  {
    "answer": "Ya, bantuan diberikan sesuai periode program.",
    "category_id": 5,
    "question": "Apakah bantuan sosial bersifat sementara?"
  },
  {
    "answer": "Pengaduan dapat disampaikan langsung ke kelurahan.",
    "category_id": 6,
    "question": "Bagaimana cara menyampaikan pengaduan warga?"
  },
  {
    "answer": "Ya, untuk memudahkan tindak lanjut.",
    "category_id": 6,
    "question": "Apakah pengaduan harus disertai identitas?"
  },
  {
    "answer": "Tergantung jenis dan tingkat pengaduan.",
    "category_id": 6,
    "question": "Berapa lama pengaduan ditindaklanjuti?"
  },
  {
    "answer": "Dapat disampaikan oleh perwakilan warga.",
    "category_id": 6,
    "question": "Apakah pengaduan dapat diwakilkan?"
  },
  {
    "answer": "Ya, aspirasi warga dapat disampaikan secara langsung.",
    "category_id": 6,
    "question": "Apakah kelurahan menerima aspirasi warga?"
  },
  {
    "answer": "Aspirasi diteruskan sesuai kewenangan.",
    "category_id": 6,
    "question": "Apakah aspirasi akan ditindaklanjuti?"
  },
  {
    "answer": "Pengaduan diproses sesuai ketentuan.",
    "category_id": 6,
    "question": "Apakah semua pengaduan diproses?"
  },
  {
    "answer": "Dapat dibatalkan dengan pemberitahuan.",
    "category_id": 6,
    "question": "Apakah pengaduan bisa dibatalkan?"
  },
  {
    "answer": "Ya, dapat disampaikan secara lisan atau tertulis.",
    "category_id": 6,
    "question": "Apakah pengaduan bisa disampaikan secara tertulis?"
  },
  {
    "question": "apa itu lorem ipsum",
    "answer": "<strong><p>The standard Lorem Ipsum passage, used since the 1500s<br></strong>\n\"Lorem ipsum dolor sit amet, consectetur adipiscing elit, sed do eiusmod tempor incididunt ut labore et dolore magna aliqua. Ut enim ad minim veniam, quis nostrud exercitation ullamco laboris nisi ut aliquip ex ea commodo consequat. Duis aute irure dolor in reprehenderit in voluptate velit esse cillum dolore eu fugiat nulla pariatur. Excepteur sint occaecat cupidatat non proident, sunt in culpa qui officia deserunt mollit anim id est laborum.\"</p>\n\n<p>Section 1.10.32 of \"de Finibus Bonorum et Malorum\", written by Cicero in 45 BC<br>\n\"Sed ut perspiciatis unde omnis iste natus error sit voluptatem accusantium doloremque laudantium",
    "category_id": 7
  }
]